apa102/__init__.py
apa102-0.0.3.dist-info/LICENSE.txt
apa102-0.0.3.dist-info/METADATA
apa102-0.0.3.dist-info/WHEEL
apa102-0.0.3.dist-info/top_level.txt
apa102-0.0.3.dist-info/RECORD
